[
    {
        "name": "A. Select two of the following:",
        "child": [
            {
                "name": "",
                "child": [
                    "HISTORY 70B",
                    "EURO ST 9",
                    "EURO ST 10",
                    "EURO ST S10",
                    "EURO ST 11",
                    "EURO ST S11",
                    "EURO ST 12",
                    "EURO ST 13"
                ]
            }
        ]
    },
    {
        "name": "B. Complete:",
        "child": [
            {
                "name": "",
                "child": [
                    "EURO ST 101A",
                    "EURO ST 101B"
                ]
            }
        ]
    },
    {
        "name": "In addition to requirements A and B, European Studies minors take:",
        "child": [
            {
                "name": "C. Three courses selected from a single specialization, two of which must be upper-division.",
                "child": []
            }
        ]
    },
    {
        "name": "Specializations and Approved Courses:",
        "child": [
            {
                "name": "(b) The following specializations are available in the major in European Studies:",
                "child": []
            },
            {
                "name": "Early Europe (Pre-1789)",
                "child": []
            },
            {
                "name": "Modern Europe (Post-1789)",
                "child": []
            },
            {
                "name": "French Studies",
                "child": []
            },
            {
                "name": "German Studies",
                "child": []
            },
            {
                "name": "Italian Studies",
                "child": []
            },
            {
                "name": "Russian Studies",
                "child": []
            },
            {
                "name": "Spanish Studies",
                "child": []
            }
        ]
    },
    {
        "name": "Residence Requirement for the Minor:",
        "child": [
            {
                "name": "At least four upper-division courses required for the minor must be completed successfully at UCI. By petition, two of the four may be taken through the UC Education Abroad Program, provided course content is approved by the appropriate department Undergraduate Director.",
                "child": []
            }
        ]
    }
]