[
    {
        "name": "A. Complete:",
        "child": [
            {
                "name": "",
                "child": [
                    "IN4MATX 171",
                    "IN4MATX 172",
                    [
                        "IN4MATX 173",
                        "IN4MATX 174"
                    ]
                ]
            }
        ]
    },
    {
        "name": "B. Select two Informatics, Technology, and Data Science courses from the following:",
        "child": [
            {
                "name": "",
                "child": [
                    "I&C SCI 4",
                    "I&C SCI 10",
                    "I&C SCI 20",
                    "I&C SCI 31",
                    "I&C SCI 32",
                    "I&C SCI 32A",
                    "IN4MATX 121",
                    "IN4MATX 131",
                    "IN4MATX 133",
                    [
                        "IN4MATX 173",
                        "IN4MATX 174"
                    ],
                    "IN4MATX 143",
                    "COMPSCI 111",
                    [
                        "COMPSCI 121",
                        "IN4MATX 141"
                    ],
                    "COMPSCI 122A",
                    "COMPSCI 131",
                    "COMPSCI 134",
                    "COMPSCI 145",
                    "COMPSCI 171",
                    "COMPSCI 178",
                    "IN4MATX 151",
                    "IN4MATX 161",
                    "IN4MATX 162W",
                    "STATS 7",
                    "STATS 8",
                    "STATS 67"
                ]
            }
        ]
    },
    {
        "name": "C. Select two Health Sciences courses from the following:",
        "child": [
            {
                "name": "",
                "child": [
                    "PUBHLTH 1",
                    "PUBHLTH 2",
                    "PUBHLTH 91",
                    "PUBHLTH 101",
                    "PUBHLTH 122",
                    "PUBHLTH 127",
                    "PUBHLTH 125"
                ]
            }
        ]
    },
    {
        "name": "NOTE:",
        "child": [
            {
                "name": "A student must earn a grade of C or better in all courses used to satisfy the requirements of this minor.",
                "child": []
            }
        ]
    }
]